<?xml version="1.0" encoding="UTF-8"?>
<!DOCTYPE suite SYSTEM "http://testng.org/testng-1.0.dtd">
<suite name="Regression_Suite" thread-count="3" parallel="tests">
  <listeners>
    <listener class-name="testlisteners.ListenerRegression"></listener>
  </listeners>
  <test name="SPAWidget" >
    <classes>
      <class name="testcases.pt.smook.TC_SPAHLWidget"/>
    </classes>
  </test> <!-- Test -->
  <test name="SPAPaging">
    <classes>
      <class name="testcases.pt.smook.TC_SPAHLPaging"/>
    </classes>
  </test> <!-- Test -->
</suite> <!-- Suite -->
